pseudo_cms/__init__.py
pseudo_cms/admin.py
pseudo_cms/models.py
pseudo_cms/utils.py
pseudo_cms/validators.py
pseudo_cms/migrations/0001_initial.py
pseudo_cms/migrations/__init__.py
pseudo_cms/south_migrations/0001_initial.py
pseudo_cms/south_migrations/0002_added_content_format.py
pseudo_cms/south_migrations/0003_populating_body_html.py
pseudo_cms/south_migrations/0004_added_page_tagline_field.py
pseudo_cms/south_migrations/__init__.py
pseudo_cms/templatetags/__init__.py
pseudo_cms/templatetags/pseudo_cms_tags.py
pseudo_cms/tests/__init__.py
pseudo_cms/tests/test_models.py
pseudo_cms/tests/test_templatetags.py
pseudo_cms/tests/test_utils.py
pseudo_cms/tests/test_validators.py
pseudo_cms/tests/testing_urls.py
django_pseudo_cms-0.5.0.dist-info/LICENSE
django_pseudo_cms-0.5.0.dist-info/METADATA
django_pseudo_cms-0.5.0.dist-info/WHEEL
django_pseudo_cms-0.5.0.dist-info/top_level.txt
django_pseudo_cms-0.5.0.dist-info/RECORD
