Metadata-Version: 2.1
Name: django-pseudo-cms
Version: 0.5.0
Summary: A Simple application to help add dynamic content to pages.
Home-page: https://github.com/madisona/django-pseudo-cms
Author: Aaron Madison
Author-email: UNKNOWN
License: UNKNOWN
Platform: UNKNOWN
Classifier: Development Status :: 4 - Beta
Classifier: Environment :: Web Environment
Classifier: Framework :: Django
Classifier: Intended Audience :: Developers
Classifier: License :: OSI Approved :: BSD License
Classifier: Operating System :: OS Independent
Classifier: Programming Language :: Python
Classifier: Topic :: Software Development
Classifier: Topic :: Software Development :: Libraries :: Application Frameworks
Requires-Dist: Django (<3.2,>=1.11)
Requires-Dist: django-image-helper (<0.6.0,>=0.2.1)
Requires-Dist: docutils (==0.12)
